PC/mem_addr_mux.v
module mem_addr_mux (
    input  [1:0] addr_src,
    input  [7:0] pc,
    output reg [7:0] mem_addr
);
always @(*) begin
    case (addr_src)
        2'b00: mem_addr = pc;    // normal fetch
        2'b01: mem_addr = 8'h00; // M[0] reset vector
        2'b10: mem_addr = 8'h01; // M[1] interrupt vector
        default: mem_addr = pc;
    endcase
end
endmodule

PC/pc_reg.v
module PC (
    input  clk,
    input  pc_load, pc_en,
    input  [7:0] pc_in,
    output reg [7:0] pc_out
);

 always @(posedge clk) begin
        if (pc_en) begin
            if (pc_load)
                pc_out <= pc_in;
            else
                pc_out <= pc_out + 1;
        end
    end
endmodule

PC/pc_in.v
module pc_in_mux (
    input  [1:0] pc_src,
    input  [7:0] data_out, // X[++sp]
    input  [7:0] reg_rb_d , // R[rb] from D stage (Loop , Branch)
    input  [7:0] I_out,   // M[0] or M[1]
    input  [7:0] reg_rb_ex,  // R[rb] from EX stage (Jump , Call)
    output reg [7:0] pc_in
);
always @(*) begin
    case (pc_src)
        2'b00: pc_in = reg_rb_ex;
        2'b01: pc_in = I_out;
        2'b10: pc_in = reg_rb_d;
        2'b11: pc_in = data_out;
        default: pc_in = 8'b0;
    endcase 
end
endmodule

PC/PC_CU.v
module PC_CU (
    input clk,
    input reset,
    input intr,
    input   [3:0]  opcode,
    input   [1:0]  brx,
    input  Z_flag,
    input  N_flag,
    input  C_flag,
    input  V_flag,
    output reg         pc_en,
    output reg         pc_load,
    output reg         byte_sel,
    output reg         if_en,
    output reg         instr_done,
    output reg [1:0]   pc_src,
    output reg [1:0]   addr_src    
);
localparam    
    S_RESET  = 2'd0,
    S_FETCH1 = 2'd1,
    S_FETCH2 = 2'd2,
    S_DONE   = 2'd3;

reg [1:0] state, next_state;
reg two_byte;
reg branch_taken;
reg pc_was_loaded;  // Track if PC was loaded in previous state

always @(*) begin
    two_byte = (opcode == 4'd12); // LDM, LDD, STD
end

always @(*) begin
    branch_taken = 1'b0;
    if (opcode == 4'd9) begin
        case (brx)
            2'd0: branch_taken = Z_flag; // JZ
            2'd1: branch_taken = N_flag; // JN
            2'd2: branch_taken = C_flag; // JC
            2'd3: branch_taken = V_flag; // JV
        endcase
    end
end

always @(posedge clk) begin
    if (reset)
        state <= S_RESET;
    else
        state <= next_state;
end

// Track if PC was loaded (for branches, jumps, etc.)
always @(posedge clk) begin
    if (reset)
        pc_was_loaded <= 1'b1;  // Reset loads PC
    else if (intr)
        pc_was_loaded <= 1'b1;  // Interrupt loads PC
    else if (state == S_DONE) begin
        // Check if any control flow instruction loaded PC
        if (opcode == 4'd9 && branch_taken)  // Conditional branch taken
            pc_was_loaded <= 1'b1;
        else if (opcode == 4'd10 && !Z_flag)  // LOOP taken
            pc_was_loaded <= 1'b1;
        else if (opcode == 4'd11)  // JMP, CALL, RET, RTI
            pc_was_loaded <= 1'b1;
        else
            pc_was_loaded <= 1'b0;
    end
    else
        pc_was_loaded <= 1'b0;
end

always @(*) begin
    // defaults
    pc_en      = 0;
    pc_load    = 0;
    byte_sel   = 0;
    if_en      = 0;
    instr_done = 0;
    pc_src     = 2'b00;
    addr_src   = 2'b00;
    next_state = state;

    case (state)
    // ===== RESET =====
    S_RESET: begin
        pc_en   = 1;
        pc_load = 1;
        pc_src  = 2'b01;   // I_out
        if_en   = 1;
        addr_src = 2'b01; // M[0]
    if (!reset)  
        next_state = S_FETCH1;
    else
        next_state = S_RESET;
    end
    // ===== FETCH =====
    S_FETCH1: begin
        // Only increment PC if it wasn't just loaded
        if (!pc_was_loaded) begin
            pc_en = 1;
        end
        if_en = 1;
        addr_src = 2'b00; // normal fetch

        if (two_byte)
            next_state = S_FETCH2;
        else
            next_state = S_DONE;
    end

    // ===== FETCH IMM / EA =====
    S_FETCH2: begin
        pc_en    = 1;
        if_en    = 1;
        byte_sel = 1;
        next_state = S_DONE;
    end

    // ===== EXECUTE / PC DECISION =====
    S_DONE: begin
        instr_done = 1;
        if (intr) begin
            pc_en   = 1;
            pc_load = 1;
            pc_src  = 2'b01;   // I_out
            addr_src = 2'b10; // M[1]
        end

        // ----- Conditional Branches -----
        else if (opcode == 4'd9) begin
            if (branch_taken) begin
                pc_load = 1;
                pc_en = 1;
                pc_src  = 2'b00; // R[rb]ex
            end
        end

        // ----- LOOP -----
        else if (opcode == 4'd10) begin
            if (!Z_flag) begin
                pc_load = 1;
                pc_en = 1;
                pc_src  = 2'b00; // R[rb]ex
            end
        end

        // ----- JMP / CALL -----
        else if (opcode == 4'd11 && brx < 2) begin
            pc_load = 1;
            pc_en = 1;
            pc_src  = 2'b10; // R[rb]d
        end

        // ----- RET / RTI -----
        else if (opcode == 4'd11 && brx >= 2) begin
            pc_load = 1;
            pc_en = 1;
            pc_src  = 2'b11; // data_out
        end
	if(intr)
        next_state = S_DONE;
	else
        next_state = S_FETCH1;
    end

    endcase
end

endmodule

PC/pc_if_tb.v
`timescale 1ns/1ps

module tb_pc_system;

    // Clock and Reset
    reg clk;
    reg reset;
    reg intr;

    // Decode signals (from execute stage)
    reg [3:0] opcode;
    reg [1:0] brx;

    // Flags
    reg Z_flag, N_flag, C_flag, V_flag;

    // Register and stack inputs
    reg [7:0] data_out;    // Stack value for RET/RTI
    reg [7:0] reg_rb_d;    // R[rb] from decode stage
    reg [7:0] reg_rb_ex;   // R[rb] from execute stage

    // Memory simulation
    reg [7:0] memory [0:255];
    wire [7:0] I_out;      // Memory data output
    
    // PC outputs
    wire [7:0] pc_out;
    wire [7:0] mem_addr;

    // Control signals
    wire pc_en;
    wire pc_load;
    wire byte_sel;
    wire if_en;
    wire instr_done;
    wire [1:0] pc_src;
    wire [1:0] addr_src;

    // Internal signals
    wire [7:0] pc_in;

    // ================= Module Instantiations =================
    
    PC_CU control_unit (
        .clk(clk),
        .reset(reset),
        .intr(intr),
        .opcode(opcode),
        .brx(brx),
        .Z_flag(Z_flag),
        .N_flag(N_flag),
        .C_flag(C_flag),
        .V_flag(V_flag),
        .pc_en(pc_en),
        .pc_load(pc_load),
        .byte_sel(byte_sel),
        .if_en(if_en),
        .instr_done(instr_done),
        .pc_src(pc_src),
        .addr_src(addr_src)
    );
    
    pc_in_mux pc_mux (
        .pc_src(pc_src),
        .data_out(data_out),
        .reg_rb_d(reg_rb_d),
        .I_out(I_out),
        .reg_rb_ex(reg_rb_ex),
        .pc_in(pc_in)
    );
    
    PC program_counter (
        .clk(clk),
        .pc_load(pc_load),
        .pc_en(pc_en),
        .pc_in(pc_in),
        .pc_out(pc_out)
    );
    
    mem_addr_mux addr_mux (
        .addr_src(addr_src),
        .pc(pc_out),
        .mem_addr(mem_addr)
    );

    // ================= Memory Model =================
    assign I_out = memory[mem_addr];

    // ================= Clock Generation =================
    initial begin
        clk = 0;
        forever #10 clk = ~clk;  // 20ns period (50MHz)
    end

    // ================= VCD Dump =================
    initial begin
        $dumpfile("pc_system_tb.vcd");
        $dumpvars(0, tb_pc_system);
    end

    // Test scenario counter
    integer test_num;
    integer pass_count;
    integer fail_count;

    // ================= Main Test =================
    initial begin
        // Initialize signals
        reset = 0;
        intr = 0;
        opcode = 4'b0000;
        brx = 2'b00;
        Z_flag = 0;
        N_flag = 0;
        C_flag = 0;
        V_flag = 0;
        data_out = 8'h00;
        reg_rb_d = 8'h00;
        reg_rb_ex = 8'h00;
        test_num = 0;
        pass_count = 0;
        fail_count = 0;

        // Initialize memory
        initialize_memory();

        // Display header
        $display("\n========================================");
        $display("  PC SYSTEM TESTBENCH");
        $display("========================================\n");

        // Test 1: Reset Sequence
        test_num = 1;
        $display("Test %0d: Reset Sequence", test_num);
        reset = 1;
        repeat(3) @(posedge clk);
        reset = 0;
        @(posedge clk);
        check_pc(8'h10, "After reset, PC should load M[0] = 0x10");

        // Test 2: Single-byte instruction (NOP)
        test_num = 2;
        $display("\nTest %0d: Single-byte instruction (NOP)", test_num);
        opcode = 4'h0;  // NOP
        wait_for_instr_done();
        check_pc(8'h11, "PC should increment by 1");

        // Test 3: Another NOP
        test_num = 3;
        $display("\nTest %0d: Another NOP", test_num);
        opcode = 4'h0;
        wait_for_instr_done();
        check_pc(8'h12, "PC should increment to 0x12");

        // Test 4: Two-byte instruction (LDM)
        test_num = 4;
        $display("\nTest %0d: Two-byte instruction (LDM)", test_num);
        opcode = 4'hC;  // LDM (opcode=12)
        wait_for_instr_done();
        check_pc(8'h14, "PC should increment by 2 (now at 0x14)");

        // Test 5: Another 2-byte instruction (LDD)
        test_num = 5;
        $display("\nTest %0d: Two-byte instruction (LDD)", test_num);
        opcode = 4'hC;  // LDD
        wait_for_instr_done();
        check_pc(8'h16, "PC should increment by 2 (now at 0x16)");

        // Test 6: Conditional branch NOT taken (JZ with Z=0)
        test_num = 6;
        $display("\nTest %0d: Conditional branch NOT taken (JZ, Z=0)", test_num);
        Z_flag = 0;
        opcode = 4'd9;  // Conditional branch
        brx = 2'd0;     // JZ
        wait_for_instr_done();
        check_pc(8'h17, "PC should increment normally by 1");

        // Test 7: Conditional branch TAKEN (JZ with Z=1)
        test_num = 7;
        $display("\nTest %0d: Conditional branch TAKEN (JZ, Z=1)", test_num);
        Z_flag = 1;
        reg_rb_ex = 8'h20;  // Jump target
        opcode = 4'd9;
        brx = 2'd0;
        wait_for_instr_done();
        check_pc(8'h20, "PC should jump to R[rb]=0x20");

        // Test 8: Instruction after jump
        test_num = 8;
        $display("\nTest %0d: Instruction after jump", test_num);
        Z_flag = 0;
        opcode = 4'd0;  // NOP
        wait_for_instr_done();
        check_pc(8'h21, "PC should increment from jump target");

        // Test 9: JMP instruction (unconditional)
        test_num = 9;
        $display("\nTest %0d: Unconditional jump (JMP)", test_num);
        reg_rb_d = 8'h30;
        opcode = 4'd11;
        brx = 2'd0;  // JMP
        wait_for_instr_done();
        check_pc(8'h30, "PC should jump to R[rb]=0x30");

        // Test 10: CALL instruction
        test_num = 10;
        $display("\nTest %0d: CALL instruction", test_num);
        reg_rb_d = 8'h40;
        opcode = 4'd11;
        brx = 2'd1;  // CALL
        wait_for_instr_done();
        check_pc(8'h40, "PC should jump to subroutine at 0x40");

        // Test 11: RET instruction
        test_num = 11;
        $display("\nTest %0d: RET instruction", test_num);
        data_out = 8'h50;  // Return address from stack
        opcode = 4'd11;
        brx = 2'd2;  // RET
        wait_for_instr_done();
        check_pc(8'h50, "PC should return from stack to 0x50");

        // Test 12: LOOP instruction (continue looping, Z=0)
        test_num = 12;
        $display("\nTest %0d: LOOP instruction (continue looping)", test_num);
        Z_flag = 0;  // Counter not zero
        reg_rb_ex = 8'h60;
        opcode = 4'd10;  // LOOP
        wait_for_instr_done();
        check_pc(8'h60, "PC should loop back to 0x60");

        // Test 13: LOOP instruction (exit loop, Z=1)
        test_num = 13;
        $display("\nTest %0d: LOOP instruction (exit loop)", test_num);
        Z_flag = 1;  // Counter is zero
        opcode = 4'd10;
        wait_for_instr_done();
        check_pc(8'h61, "PC should continue normally to 0x61");

        // Test 14: Interrupt handling
        test_num = 14;
        $display("\nTest %0d: Interrupt handling", test_num);
        Z_flag = 0;
        opcode = 4'd0;  // Normal instruction
        wait(control_unit.state == 2'd1);  // FETCH1
        @(posedge clk);
        intr = 1;
        wait(control_unit.state == 2'd3);  // DONE
        @(posedge clk);  
        intr = 0;
        @(posedge clk);  
        check_pc(8'h70, "PC should jump to interrupt vector M[1] = 0x70");
       
        // Test 15: Instruction at interrupt handler
        test_num = 15;
        $display("\nTest %0d: Instruction at interrupt handler", test_num);
        opcode = 4'd0;  // NOP
        wait_for_instr_done();
        check_pc(8'h71, "PC should increment to 0x71");

        // Test 16: RTI instruction
        test_num = 16;
        $display("\nTest %0d: RTI instruction", test_num);
        data_out = 8'h80;  // Return address
        opcode = 4'd11;
        brx = 2'd3;  // RTI
        wait_for_instr_done();
        check_pc(8'h80, "PC should return from interrupt to 0x80");

        // Test 17: Sequential instructions
        test_num = 17;
        $display("\nTest %0d: Sequential 1-byte instructions", test_num);
        opcode = 4'd0;
        wait_for_instr_done();
        check_pc(8'h81, "First increment to 0x81");
        wait_for_instr_done();
        check_pc(8'h82, "Second increment to 0x82");
        wait_for_instr_done();
        check_pc(8'h83, "Third increment to 0x83");

        // Test 18: JN with N=1
        test_num = 18;
        $display("\nTest %0d: JN branch taken (N=1)", test_num);
        N_flag = 1;
        reg_rb_ex = 8'h90;
        opcode = 4'd9;
        brx = 2'd1;  // JN
        wait_for_instr_done();
        check_pc(8'h90, "PC should jump on negative flag");

        // Test 19: JC with C=1
        test_num = 19;
        $display("\nTest %0d: JC branch taken (C=1)", test_num);
        N_flag = 0;
        C_flag = 1;
        reg_rb_ex = 8'hA0;
        opcode = 4'd9;
        brx = 2'd2;  // JC
        wait_for_instr_done();
        check_pc(8'hA0, "PC should jump on carry flag");

        // Test 20: JV with V=1
        test_num = 20;
        $display("\nTest %0d: JV branch taken (V=1)", test_num);
        C_flag = 0;
        V_flag = 1;
        reg_rb_ex = 8'hB0;
        opcode = 4'd9;
        brx = 2'd3;  // JV
        wait_for_instr_done();
        check_pc(8'hB0, "PC should jump on overflow flag");

        // Test 21: JN with N=0 (not taken)
        test_num = 21;
        $display("\nTest %0d: JN branch NOT taken (N=0)", test_num);
        N_flag = 0;
        V_flag = 0;
        opcode = 4'd9;
        brx = 2'd1;  // JN
        wait_for_instr_done();
        check_pc(8'hB1, "PC should increment normally");

        // Test 22: Memory addressing during reset
        test_num = 22;
        $display("\nTest %0d: Memory addressing verification", test_num);
        reset = 1;
        @(posedge clk);
        @(posedge clk);  // Wait for FSM to enter RESET state
        if (addr_src == 2'b01 && mem_addr == 8'h00) begin
            $display("  [PASS] Reset uses M[0] (addr_src=01, mem_addr=0x00)");
            pass_count = pass_count + 1;
        end else begin
            $display("  [FAIL] Reset addressing incorrect (addr_src=%b, mem_addr=0x%h)", addr_src, mem_addr);
            fail_count = fail_count + 1;
        end
        reset = 0;
        //repeat(3) @(posedge clk);

        // Test 23: Interrupt addressing
        test_num = 23;
        $display("\nTest %0d: Interrupt memory addressing", test_num);
        opcode = 4'd0;
        wait(control_unit.state == 2'd1);  // Wait for FETCH1
        @(posedge clk);
        intr = 1;
        @(posedge clk);  // Let FSM process interrupt
        wait(control_unit.state == 2'd3);  // Wait for DONE state
        #1;  // Small delay for combinational logic to settle
        if (addr_src == 2'b10 && mem_addr == 8'h01) begin
            $display("  [PASS] Interrupt uses M[1] (addr_src=10, mem_addr=0x01)");
            pass_count = pass_count + 1;
        end else begin
            $display("  [FAIL] Interrupt addressing incorrect (addr_src=%b, mem_addr=0x%h)", addr_src, mem_addr);
            fail_count = fail_count + 1;
        end
        intr = 0;
        //repeat(2) @(posedge clk);

        // Summary
        $display("\n========================================");
        $display("  TEST SUMMARY");
        $display("========================================");
        $display("  Total Tests: %0d", pass_count + fail_count);
        $display("  Passed: %0d", pass_count);
        $display("  Failed: %0d", fail_count);
        if (fail_count == 0)
            $display("  Status: ALL TESTS PASSED!");
        else
            $display("  Status: SOME TESTS FAILED!");
        $display("========================================\n");

        #100;
        $stop;
    end

    // ================= Helper Tasks =================

    // Initialize memory with test data
    task initialize_memory;
        integer i;
        begin
            // Clear memory
            for (i = 0; i < 256; i = i + 1)
                memory[i] = 8'h00;

            // Reset and interrupt vectors
            memory[8'h00] = 8'h10;  // M[0] = 0x10 (reset vector)
            memory[8'h01] = 8'h70;  // M[1] = 0x70 (interrupt vector)

            // Test program starting at 0x10
            memory[8'h10] = 8'h00;  // NOP
            memory[8'h11] = 8'h29;  // ADD R2, R1
            memory[8'h12] = 8'hC1;  // LDM R1, #0x55
            memory[8'h13] = 8'h55;  // Immediate value
            memory[8'h14] = 8'hC6;  // LDD R2, [0xAA]
            memory[8'h15] = 8'hAA;  // Effective address
            memory[8'h16] = 8'h90;  // JZ R0
            memory[8'h17] = 8'h91;  // JZ R1
            
            // Jump target locations
            memory[8'h20] = 8'hCC;
            memory[8'h21] = 8'hBB;
            memory[8'h30] = 8'hDD;
            memory[8'h40] = 8'hEE;
            memory[8'h50] = 8'h11;
            memory[8'h60] = 8'hFF;
            memory[8'h61] = 8'h22;
            memory[8'h70] = 8'h33;  // Interrupt handler
            memory[8'h71] = 8'h44;
            memory[8'h80] = 8'h55;  // Return from interrupt
            memory[8'h81] = 8'h66;
            memory[8'h82] = 8'h77;
            memory[8'h83] = 8'h88;
            memory[8'h90] = 8'h99;  // JN target
            memory[8'hA0] = 8'hAA;  // JC target
            memory[8'hB0] = 8'hBB;  // JV target
            memory[8'hB1] = 8'hCC;
        end
    endtask

    // Wait for instruction completion
    task wait_for_instr_done;
        begin
            @(posedge instr_done);
            @(negedge clk);
        end
    endtask

    // Check PC value
    task check_pc;
        input [7:0] expected;
        input [80*8:1] msg;
        begin
            if (pc_out !== expected) begin
                $display("  [FAIL] PC Check: %s", msg);
                $display("         Expected: 0x%02h, Got: 0x%02h", expected, pc_out);
                fail_count = fail_count + 1;
            end else begin
                $display("  [PASS] PC = 0x%02h - %s", pc_out, msg);
                pass_count = pass_count + 1;
            end
        end
    endtask

    // ================= Monitors =================

    // State transition monitor
    always @(posedge clk) begin
        if (control_unit.state != control_unit.next_state)
            $display("    [State] %0d -> %0d | PC=0x%02h | pc_was_loaded=%b", 
                     control_unit.state, control_unit.next_state, pc_out, control_unit.pc_was_loaded);
    end

    // Control signal monitor
    always @(posedge clk) begin
        if (pc_load)
            $display("    [PC Load] pc_in=0x%02h (src=%b) -> PC will be 0x%02h next cycle", 
                     pc_in, pc_src, pc_in);
    end

endmodule

PC/pc_system_tb.vcd
$date
	Wed Dec 17 04:25:57 2025
$end
$version
	ModelSim Version 10.6d
$end
$timescale
	1ps
$end

$scope module tb_pc_system $end
$var reg 1 ! clk $end
$var reg 1 " reset $end
$var reg 1 # intr $end
$var reg 4 $ opcode [3:0] $end
$var reg 2 % brx [1:0] $end
$var reg 1 & Z_flag $end
$var reg 1 ' N_flag $end
$var reg 1 ( C_flag $end
$var reg 1 ) V_flag $end
$var reg 8 * data_out [7:0] $end
$var reg 8 + reg_rb_d [7:0] $end
$var reg 8 , reg_rb_ex [7:0] $end
$var wire 1 - I_out [7] $end
$var wire 1 . I_out [6] $end
$var wire 1 / I_out [5] $end
$var wire 1 0 I_out [4] $end
$var wire 1 1 I_out [3] $end
$var wire 1 2 I_out [2] $end
$var wire 1 3 I_out [1] $end
$var wire 1 4 I_out [0] $end
$var wire 1 5 pc_out [7] $end
$var wire 1 6 pc_out [6] $end
$var wire 1 7 pc_out [5] $end
$var wire 1 8 pc_out [4] $end
$var wire 1 9 pc_out [3] $end
$var wire 1 : pc_out [2] $end
$var wire 1 ; pc_out [1] $end
$var wire 1 < pc_out [0] $end
$var wire 1 = mem_addr [7] $end
$var wire 1 > mem_addr [6] $end
$var wire 1 ? mem_addr [5] $end
$var wire 1 @ mem_addr [4] $end
$var wire 1 A mem_addr [3] $end
$var wire 1 B mem_addr [2] $end
$var wire 1 C mem_addr [1] $end
$var wire 1 D mem_addr [0] $end
$var wire 1 E pc_en $end
$var wire 1 F pc_load $end
$var wire 1 G byte_sel $end
$var wire 1 H if_en $end
$var wire 1 I instr_done $end
$var wire 1 J pc_src [1] $end
$var wire 1 K pc_src [0] $end
$var wire 1 L addr_src [1] $end
$var wire 1 M addr_src [0] $end
$var wire 1 N pc_in [7] $end
$var wire 1 O pc_in [6] $end
$var wire 1 P pc_in [5] $end
$var wire 1 Q pc_in [4] $end
$var wire 1 R pc_in [3] $end
$var wire 1 S pc_in [2] $end
$var wire 1 T pc_in [1] $end
$var wire 1 U pc_in [0] $end
$var integer 32 V test_num $end
$var integer 32 W pass_count $end
$var integer 32 X fail_count $end

$scope task initialize_memory $end
$var integer 32 Y i $end
$upscope $end

$scope task wait_for_instr_done $end
$upscope $end

$scope task check_pc $end
$var reg 8 Z expected [7:0] $end
$var reg 640 [ msg [640:1] $end
$upscope $end

$scope module control_unit $end
$var parameter 2 \ S_RESET $end
$var parameter 2 ] S_FETCH1 $end
$var parameter 2 ^ S_FETCH2 $end
$var parameter 2 _ S_DONE $end
$var wire 1 ` clk $end
$var wire 1 a reset $end
$var wire 1 b intr $end
$var wire 1 c opcode [3] $end
$var wire 1 d opcode [2] $end
$var wire 1 e opcode [1] $end
$var wire 1 f opcode [0] $end
$var wire 1 g brx [1] $end
$var wire 1 h brx [0] $end
$var wire 1 i Z_flag $end
$var wire 1 j N_flag $end
$var wire 1 k C_flag $end
$var wire 1 l V_flag $end
$var reg 1 m pc_en $end
$var reg 1 n pc_load $end
$var reg 1 o byte_sel $end
$var reg 1 p if_en $end
$var reg 1 q instr_done $end
$var reg 2 r pc_src [1:0] $end
$var reg 2 s addr_src [1:0] $end
$var reg 2 t state [1:0] $end
$var reg 2 u next_state [1:0] $end
$var reg 1 v two_byte $end
$var reg 1 w branch_taken $end
$var reg 1 x pc_was_loaded $end
$upscope $end

$scope module pc_mux $end
$var wire 1 J pc_src [1] $end
$var wire 1 K pc_src [0] $end
$var wire 1 y data_out [7] $end
$var wire 1 z data_out [6] $end
$var wire 1 { data_out [5] $end
$var wire 1 | data_out [4] $end
$var wire 1 } data_out [3] $end
$var wire 1 ~ data_out [2] $end
$var wire 1 !! data_out [1] $end
$var wire 1 "! data_out [0] $end
$var wire 1 #! reg_rb_d [7] $end
$var wire 1 $! reg_rb_d [6] $end
$var wire 1 %! reg_rb_d [5] $end
$var wire 1 &! reg_rb_d [4] $end
$var wire 1 '! reg_rb_d [3] $end
$var wire 1 (! reg_rb_d [2] $end
$var wire 1 )! reg_rb_d [1] $end
$var wire 1 *! reg_rb_d [0] $end
$var wire 1 - I_out [7] $end
$var wire 1 . I_out [6] $end
$var wire 1 / I_out [5] $end
$var wire 1 0 I_out [4] $end
$var wire 1 1 I_out [3] $end
$var wire 1 2 I_out [2] $end
$var wire 1 3 I_out [1] $end
$var wire 1 4 I_out [0] $end
$var wire 1 +! reg_rb_ex [7] $end
$var wire 1 ,! reg_rb_ex [6] $end
$var wire 1 -! reg_rb_ex [5] $end
$var wire 1 .! reg_rb_ex [4] $end
$var wire 1 /! reg_rb_ex [3] $end
$var wire 1 0! reg_rb_ex [2] $end
$var wire 1 1! reg_rb_ex [1] $end
$var wire 1 2! reg_rb_ex [0] $end
$var reg 8 3! pc_in [7:0] $end
$upscope $end

$scope module program_counter $end
$var wire 1 4! clk $end
$var wire 1 F pc_load $end
$var wire 1 E pc_en $end
$var wire 1 N pc_in [7] $end
$var wire 1 O pc_in [6] $end
$var wire 1 P pc_in [5] $end
$var wire 1 Q pc_in [4] $end
$var wire 1 R pc_in [3] $end
$var wire 1 S pc_in [2] $end
$var wire 1 T pc_in [1] $end
$var wire 1 U pc_in [0] $end
$var reg 8 5! pc_out [7:0] $end
$upscope $end

$scope module addr_mux $end
$var wire 1 L addr_src [1] $end
$var wire 1 M addr_src [0] $end
$var wire 1 5 pc [7] $end
$var wire 1 6 pc [6] $end
$var wire 1 7 pc [5] $end
$var wire 1 8 pc [4] $end
$var wire 1 9 pc [3] $end
$var wire 1 : pc [2] $end
$var wire 1 ; pc [1] $end
$var wire 1 < pc [0] $end
$var reg 8 6! mem_addr [7:0] $end
$upscope $end
$upscope $end
$enddefinitions $end
#0
$dumpvars
0!
1"
0#
b0 $
b0 %
0&
0'
0(
0)
b0 *
b0 +
b0 ,
0m
0n
0o
0p
0q
b0 r
b0 s
bx t
bx u
0v
0w
xx
b0 3!
bx 5!
bx 6!
bx Z
bx [
b0 \
b1 ]
b10 ^
b11 _
b1 V
b0 W
b0 X
b100000000 Y
x4
x3
x2
x1
x0
x/
x.
x-
x<
x;
x:
x9
x8
x7
x6
x5
xD
xC
xB
xA
x@
x?
x>
x=
0E
0F
0G
0H
0I
0K
0J
0M
0L
0U
0T
0S
0R
0Q
0P
0O
0N
04!
02!
01!
00!
0/!
0.!
0-!
0,!
0+!
0*!
0)!
0(!
0'!
0&!
0%!
0$!
0#!
0"!
0!!
0~
0}
0|
0{
0z
0y
0l
0k
0j
0i
0h
0g
0f
0e
0d
0c
0b
1a
0`
$end
#10000
1!
1`
14!
b0 t
1x
b0 u
1m
1n
b1 r
1p
b1 s
1E
1F
1H
1M
1K
bx 3!
b0 6!
0D
0C
0B
0A
0@
0?
0>
0=
xU
xT
xS
xR
xQ
xP
xO
xN
04
03
02
01
10
0/
0.
0-
b10000 3!
0U
0T
0S
0R
1Q
0P
0O
0N
#20000
0!
0`
04!
#30000
1!
1`
14!
b10000 5!
0<
0;
0:
09
18
07
06
05
#40000
0!
0`
04!
#50000
1!
1`
14!
0"
0a
0m
0n
0p
b0 r
b0 s
1m
1n
b1 r
1p
b1 s
b1 u
#60000
0!
0`
04!
#70000
1!
1`
14!
b10000 Z
b10000010110011001110100011001010111001000100000011100100110010101110011011001010111010000101100001000000101000001000011001000000111001101101000011011110111010101101100011001000010000001101100011011110110000101100100001000000100110101011011001100000101110100100000001111010010000000110000011110000011000100110000 [
b1 W
b10 V
b1 t
0x
0m
0n
0p
b0 r
b0 s
1m
1p
b11 u
0F
0M
0K
b0 3!
b10000 6!
1@
0Q
00
#80000
0!
0`
04!
#90000
1!
1`
14!
b10001 5!
b11 t
1<
b10001 6!
0m
0p
1q
b1 u
1D
0E
0H
1I
14
11
1/
#100000
0!
0`
04!
b10001 Z
b10100000100001100100000011100110110100001101111011101010110110001100100001000000110100101101110011000110111001001100101011011010110010101101110011101000010000001100010011110010010000000110001 [
b10 W
b11 V
#110000
1!
1`
14!
b1 t
0q
1m
1p
b11 u
1E
1H
0I
#120000
0!
0`
04!
#130000
1!
1`
14!
b10010 5!
b11 t
0<
1;
b10010 6!
0m
0p
1q
b1 u
0D
1C
0E
0H
1I
01
0/
1.
1-
#140000
0!
0`
04!
b10010 Z
b10100000100001100100000011100110110100001101111011101010110110001100100001000000110100101101110011000110111001001100101011011010110010101101110011101000010000001110100011011110010000000110000011110000011000100110010 [
b11 W
b100 V
b1100 $
1d
1c
1v
0q
b11 u
1q
b1 u
#150000
1!
1`
14!
b1 t
0q
1m
1p
b10 u
1E
1H
0I
#160000
0!
0`
04!
#170000
1!
1`
14!
b10011 5!
b10 t
1<
b10011 6!
0m
0p
1m
1p
1o
b11 u
1D
1G
12
10
0-
#180000
0!
0`
04!
#190000
1!
1`
14!
b10100 5!
b11 t
0<
0;
1:
b10100 6!
0m
0o
0p
1q
b1 u
0D
0C
1B
0E
0G
0H
1I
04
13
00
1-
#200000
0!
0`
04!
b10100 Z
b101000001000011001000000111001101101000011011110111010101101100011001000010000001101001011011100110001101110010011001010110110101100101011011100111010000100000011000100111100100100000001100100010000000101000011011100110111101110111001000000110000101110100001000000011000001111000001100010011010000101001 [
b100 W
b101 V
#210000
1!
1`
14!
b1 t
0q
1m
1p
b10 u
1E
1H
0I
#220000
0!
0`
04!
#230000
1!
1`
14!
b10101 5!
b10 t
1<
b10101 6!
0m
0p
1m
1p
1o
b11 u
1D
1G
02
11
1/
0.
#240000
0!
0`
04!
#250000
1!
1`
14!
b10110 5!
b11 t
0<
1;
b10110 6!
0m
0o
0p
1q
b1 u
0D
1C
0E
0G
0H
1I
03
01
10
0/
#260000
0!
0`
04!
b10110 Z
b101000001000011001000000111001101101000011011110111010101101100011001000010000001101001011011100110001101110010011001010110110101100101011011100111010000100000011000100111100100100000001100100010000000101000011011100110111101110111001000000110000101110100001000000011000001111000001100010011011000101001 [
b101 W
b110 V
b1001 $
1f
0d
0v
0q
b11 u
1q
b1 u
#270000
1!
1`
14!
b1 t
0q
1m
1p
b11 u
1E
1H
0I
#280000
0!
0`
04!
#290000
1!
1`
14!
b10111 5!
b11 t
1<
b10111 6!
0m
0p
1q
b1 u
1D
0E
0H
1I
14
#300000
0!
0`
04!
b10111 Z
b10100000100001100100000011100110110100001101111011101010110110001100100001000000110100101101110011000110111001001100101011011010110010101101110011101000010000001101110011011110111001001101101011000010110110001101100011110010010000001100010011110010010000000110001 [
b110 W
b111 V
1&
b100000 ,
1i
1-!
b100000 3!
1w
0q
b11 u
1q
1n
1m
b1 u
1P
1F
1E
#310000
1!
1`
14!
b100000 5!
b1 t
1x
0<
0;
0:
08
17
b100000 6!
0m
0n
0q
1p
b11 u
0D
0C
0B
0@
1?
0E
0F
1H
0I
04
12
11
00
1.
#320000
0!
0`
04!
#330000
1!
1`
14!
b11 t
0x
0p
1q
1n
1m
b1 u
0H
1F
1E
1I
#340000
0!
0`
04!
b100000 Z
b1010000010000110010000001110011011010000110111101110101011011000110010000100000011010100111010101101101011100000010000001110100011011110010000001010010010110110111001001100010010111010011110100110000011110000011001000110000 [
b111 W
b1000 V
0&
b0 $
0i
0f
0c
0w
0m
0n
0q
b11 u
1q
b1 u
0E
0F
#350000
1!
1`
14!
b1 t
0q
1m
1p
b11 u
1E
1H
0I
#360000
0!
0`
04!
#370000
1!
1`
14!
b100001 5!
b11 t
1<
b100001 6!
0m
0p
1q
b1 u
1D
0E
0H
1I
14
13
02
10
1/
0.
#380000
0!
0`
04!
b100001 Z
b10100000100001100100000011100110110100001101111011101010110110001100100001000000110100101101110011000110111001001100101011011010110010101101110011101000010000001100110011100100110111101101101001000000110101001110101011011010111000000100000011101000110000101110010011001110110010101110100 [
b1000 W
b1001 V
b110000 +
b1011 $
1f
1e
1c
1&!
1%!
0q
b11 u
1q
1n
1m
b10 r
b1 u
1F
1E
1J
b110000 3!
1Q
#390000
1!
1`
14!
b110000 5!
b1 t
1x
0<
18
b110000 6!
0m
0n
0q
b0 r
1p
b11 u
0D
1@
0E
0F
1H
0I
03
12
0/
1.
0J
b100000 3!
0Q
#400000
0!
0`
04!
#410000
1!
1`
14!
b11 t
0x
0p
1q
1n
1m
b10 r
b1 u
0H
1F
1E
1I
1J
b110000 3!
1Q
